opyration/__init__.py
opyration/interfaces.py
opyration/operation.py
opyration/results.py
opyration/symbols.py
opyration/transaction.py
opyration-0.2.6.dist-info/METADATA
opyration-0.2.6.dist-info/WHEEL
opyration-0.2.6.dist-info/RECORD
